LICENSE.txt
README.md
setup.cfg
setup.py
cpflow/__init__.py
cpflow/circuit_assembly.py
cpflow/cp_utils.py
cpflow/exact_decompositions.py
cpflow/gates.py
cpflow/main.py
cpflow/matrix_utils.py
cpflow/optimization.py
cpflow/penalty.py
cpflow/topology.py
cpflow/trigonometric_utils.py
cpflow.egg-info/PKG-INFO
cpflow.egg-info/SOURCES.txt
cpflow.egg-info/dependency_links.txt
cpflow.egg-info/requires.txt
cpflow.egg-info/top_level.txt