Metadata-Version: 2.1
Name: cpflow
Version: 0.0.1
Summary: Variational synthesis of quantum circuits
Home-page: https://github.com/idnm/cpflow
Author: Nikita Nemkov
Author-email: nnemkov@gmail.com
License: MIT
Platform: UNKNOWN
License-File: LICENSE.txt
